flask_weaviate/__init__.py
flask_weaviate-1.1.0.dist-info/LICENSE
flask_weaviate-1.1.0.dist-info/METADATA
flask_weaviate-1.1.0.dist-info/WHEEL
flask_weaviate-1.1.0.dist-info/top_level.txt
flask_weaviate-1.1.0.dist-info/RECORD
