Metadata-Version: 2.1
Name: flask_weaviate
Version: 1.1.0
Summary: Flask extension for Weaviate
Author-email: Evert Jan Stamhuis <ej@fromej.nl>
License: Copyright (c) 2024 Evert Jan Stamhuis
Project-URL: documentation, https://github.com/evertjstam/flask-weaviate
Project-URL: homepage, https://github.com/evertjstam/flask-weaviate
Project-URL: repository, https://github.com/evertjstam/flask-weaviate
Project-URL: tracker, https://github.com/evertjstam/flask-weaviate/issues
Keywords: flask,weaviate,flask-extension
Classifier: Development Status :: 5 - Production/Stable
Classifier: Intended Audience :: Developers
Classifier: Framework :: Flask
Classifier: License :: OSI Approved :: MIT License
Classifier: Programming Language :: Python :: 3.8
Classifier: Programming Language :: Python :: 3.9
Classifier: Programming Language :: Python :: 3.10
Classifier: Programming Language :: Python :: 3.11
Classifier: Programming Language :: Python :: 3.12
Requires-Python: >=3.8
License-File: LICENSE
Requires-Dist: flask
Requires-Dist: weaviate-client>=4.4.1
Provides-Extra: dev
Requires-Dist: flake8; extra == "dev"
Requires-Dist: isort; extra == "dev"
Requires-Dist: black; extra == "dev"
Requires-Dist: pytest; extra == "dev"
Requires-Dist: faker; extra == "dev"
Requires-Dist: coverage; extra == "dev"
Requires-Dist: build; extra == "dev"
Requires-Dist: twine; extra == "dev"
